reports_exporter/__init__.py
reports_exporter/access_token_fetcher.py
reports_exporter/arguments_parser.py
reports_exporter/custom_logging.py
reports_exporter/earnings_report_fetcher.py
reports_exporter/report_fetcher_base.py
reports_exporter/report_main.py
reports_exporter/report_type.py
reports_exporter/response_report_fetcher.py
reports_exporter/response_report_main.py
reports_exporter/utils.py
cb4_reports_exporter-2.19.0.dist-info/LICENSE
cb4_reports_exporter-2.19.0.dist-info/METADATA
cb4_reports_exporter-2.19.0.dist-info/WHEEL
cb4_reports_exporter-2.19.0.dist-info/top_level.txt
cb4_reports_exporter-2.19.0.dist-info/RECORD
