Metadata-Version: 2.1
Name: cb4-reports-exporter
Version: 2.19.0
Summary: Export reports from CB4
Home-page: UNKNOWN
Author: CB4
Author-email: support@cb4.com
License: UNKNOWN
Platform: UNKNOWN
Requires-Python: >=3.7
